options_tracker-0.1.11.data/scripts/options-file-tracker
options_tracker-0.1.11.data/scripts/options-tracker
optionstracker/__init__.py
optionstracker/config.py
optionstracker/mirriad.py
optionstracker/price.py
optionstracker/tax.py
optionstracker/value.py
optionstracker/vesting.py
options_tracker-0.1.11.dist-info/LICENSE
options_tracker-0.1.11.dist-info/METADATA
options_tracker-0.1.11.dist-info/WHEEL
options_tracker-0.1.11.dist-info/top_level.txt
options_tracker-0.1.11.dist-info/RECORD
