Metadata-Version: 2.1
Name: options-tracker
Version: 0.1.11
Summary: What are my options worth today?
Home-page: http://gitlab.com/OldIronHorse/options-tracker
Author: Simon Redding
Author-email: s1m0n.r3dd1ng@gmail.com
License: GPL3
Platform: UNKNOWN
Requires-Python: >=3.6
Requires-Dist: click
Requires-Dist: requests-html
Requires-Dist: dateparser
Requires-Dist: python-dateutil
Requires-Dist: pyyaml
Requires-Dist: tabulate
